qcompress/__init__.py
qcompress/_version.py
qcompress/config.py
qcompress/qae_engine.py
qcompress/qae_engine_test.py
qcompress/utils.py
qcompress/data/H2_sto-3g_singlet_0.2.hdf5
qcompress/data/H2_sto-3g_singlet_0.3.hdf5
qcompress/data/H2_sto-3g_singlet_0.4.hdf5
qcompress/data/H2_sto-3g_singlet_0.5.hdf5
qcompress/data/H2_sto-3g_singlet_0.6.hdf5
qcompress/data/H2_sto-3g_singlet_0.7.hdf5
qcompress/data/H2_sto-3g_singlet_0.8.hdf5
qcompress/data/H2_sto-3g_singlet_0.9.hdf5
qcompress/data/H2_sto-3g_singlet_1.0.hdf5
qcompress/data/H2_sto-3g_singlet_1.1.hdf5
qcompress/data/H2_sto-3g_singlet_1.2.hdf5
qcompress/data/H2_sto-3g_singlet_1.3.hdf5
qcompress/data/H2_sto-3g_singlet_1.4.hdf5
qcompress/data/H2_sto-3g_singlet_1.5.hdf5
qcompress/data/H2_sto-3g_singlet_1.6.hdf5
qcompress/data/H2_sto-3g_singlet_1.7.hdf5
qcompress/data/H2_sto-3g_singlet_1.8.hdf5
qcompress/data/H2_sto-3g_singlet_1.9.hdf5
qcompress/data/H2_sto-3g_singlet_2.0.hdf5
qcompress/data/H2_sto-3g_singlet_2.1.hdf5
qcompress/data/H2_sto-3g_singlet_2.2.hdf5
qcompress/data/H2_sto-3g_singlet_2.3.hdf5
qcompress/data/H2_sto-3g_singlet_2.4.hdf5
qcompress/data/H2_sto-3g_singlet_2.5.hdf5
qcompress/data/H2_sto-3g_singlet_2.6.hdf5
qcompress/data/H2_sto-3g_singlet_2.7.hdf5
qcompress/data/H2_sto-3g_singlet_2.8.hdf5
qcompress/data/H2_sto-3g_singlet_2.9.hdf5
qcompress/data/H2_sto-3g_singlet_3.0.hdf5
qcompress/data/H2_sto-3g_singlet_3.1.hdf5
qcompress/data/H2_sto-3g_singlet_3.2.hdf5
qcompress/data/H2_sto-3g_singlet_3.3.hdf5
qcompress/data/H2_sto-3g_singlet_3.4.hdf5
qcompress/data/H2_sto-3g_singlet_3.5.hdf5
qcompress/data/H2_sto-3g_singlet_3.6.hdf5
qcompress/data/H2_sto-3g_singlet_3.7.hdf5
qcompress/data/H2_sto-3g_singlet_3.8.hdf5
qcompress/data/H2_sto-3g_singlet_3.9.hdf5
qcompress/data/H2_sto-3g_singlet_4.0.hdf5
qcompress/data/H2_sto-3g_singlet_4.1.hdf5
qcompress-0.0.1.dev12.dist-info/LICENSE
qcompress-0.0.1.dev12.dist-info/METADATA
qcompress-0.0.1.dev12.dist-info/WHEEL
qcompress-0.0.1.dev12.dist-info/top_level.txt
qcompress-0.0.1.dev12.dist-info/RECORD
