Metadata-Version: 2.1
Name: qcompress
Version: 0.0.1.dev12
Summary: A Python framework for the quantum autoencoder algorithm
Home-page: https://github.com/hsim13372/QCompress
Author: hannahsim
Author-email: hsim13372@gmail.com
License: Apache-2.0
Platform: UNKNOWN
Requires-Python: >=3.6
Requires-Dist: pytest
Requires-Dist: jupyter
Requires-Dist: pyquil (>=2.0.0b1)
Requires-Dist: openfermion (>=0.7)
